Translation/__init__.py
Translation/translator.py
translatifyplux-0.3.dist-info/METADATA
translatifyplux-0.3.dist-info/WHEEL
translatifyplux-0.3.dist-info/top_level.txt
translatifyplux-0.3.dist-info/RECORD
